classes/__init__.py
classes/dbclient.py
classes/stocks.py
lb_classes-0.1.0.dist-info/WHEEL
lb_classes-0.1.0.dist-info/METADATA
lb_classes-0.1.0.dist-info/RECORD
