Metadata-Version: 2.1
Name: lb-classes
Version: 0.1.0
Summary: Implements classes for stocks model and db client
Author: Lionel Barbagallo
Requires-Python: >=3.7.10,<4.0.0
Classifier: Programming Language :: Python :: 3
Classifier: Programming Language :: Python :: 3.10
Classifier: Programming Language :: Python :: 3.8
Classifier: Programming Language :: Python :: 3.9
Requires-Dist: SQLAlchemy (>=1.4.26,<2.0.0)
Requires-Dist: postgres (>=4.0,<5.0)
Requires-Dist: psycopg2-binary (>=2.9.1,<3.0.0)
